openbadge/__init__.py
openbadge/openbadge.py
OpenBadge-0.0.1.dist-info/DESCRIPTION.rst
OpenBadge-0.0.1.dist-info/METADATA
OpenBadge-0.0.1.dist-info/metadata.json
OpenBadge-0.0.1.dist-info/RECORD
OpenBadge-0.0.1.dist-info/top_level.txt
OpenBadge-0.0.1.dist-info/WHEEL
