Metadata-Version: 2.0
Name: OpenBadge
Version: 0.0.1
Summary: An Open Badges helper library
Home-page: https://github.com/thisbejim/openbadge
Author: James Childs-Maidment
Author-email: jchildsmaidment@outlook.com
License: MIT
Keywords: Open Badges
Platform: UNKNOWN
Classifier: Development Status :: 3 - Alpha
Classifier: Intended Audience :: Developers
Classifier: License :: OSI Approved :: MIT License
Classifier: Programming Language :: Python
Requires-Dist: PyJWT
Requires-Dist: cryptography
Requires-Dist: hashlib
